MANIFEST.in
README.md
VERSION
setup.py
aiogettext/__init__.py
aiogettext/languagecontext.py
aiogettext/loader.py
aiogettext/package.json
aiogettext/translation.py
aiogettext/translationcatalog.py
aiogettext/utils.py
aiogettext.egg-info/PKG-INFO
aiogettext.egg-info/SOURCES.txt
aiogettext.egg-info/dependency_links.txt
aiogettext.egg-info/requires.txt
aiogettext.egg-info/top_level.txt
aiogettext/types/__init__.py
aiogettext/types/itranslation.py
tests/__init__.py
tests/conftest.py
tests/test_unit_languagecontext.py