Metadata-Version: 2.1
Name: aiogettext
Version: 0.0.2
Summary: Asynchronous GNU Gettext implementation.
Home-page: https://gitlab.com/webiam/lib
Author: Cochise Ruhulessin
Author-email: cochiseruhulessin@gmail.com
Classifier: Development Status :: 4 - Beta
Classifier: Environment :: Web Environment
Classifier: Intended Audience :: Developers
Classifier: Intended Audience :: Financial and Insurance Industry
Classifier: License :: Other/Proprietary License
Classifier: Operating System :: POSIX
Classifier: Operating System :: POSIX :: Linux
Classifier: Programming Language :: Python :: 3.11
Classifier: Programming Language :: Python :: 3.12
Classifier: Programming Language :: Python :: 3 :: Only
Classifier: Topic :: Internet
Classifier: Topic :: Internet :: WWW/HTTP :: Session
Classifier: Topic :: Software Development :: Libraries
Requires-Dist: aiofiles>=23.2.1
